[
  {
    "id": 421,
    "character": "衛",
    "strokes": 16,
    "readings": {
      "kun": [],
      "on": [
        {
          "furigana": "エイ",
          "romanji": "ei"
        }
      ]
    },
    "meanings": {
      "id": "kebersihan, sanitasi",
      "en": "sanitation, hygiene"
    },
    "examples": [
      {
        "word": "衛生",
        "furigana": "えいせい",
        "romanji": "eisei",
        "meanings": {
          "id": "kebersihan, sanitasi",
          "en": "sanitation, hygiene"
        },
        "id": 1
      }
    ]
  },
  {
    "id": 422,
    "character": "憶",
    "strokes": 16,
    "readings": {
      "kun": [],
      "on": [
        {
          "furigana": "オク",
          "romanji": "oku"
        }
      ]
    },
    "meanings": {
      "id": "ingatan, memori",
      "en": "memory, recollection"
    },
    "examples": [
      {
        "word": "記憶",
        "furigana": "きおく",
        "romanji": "kioku",
        "meanings": {
          "id": "ingatan, memori",
          "en": "memory, recollection"
        },
        "id": 1
      }
    ]
  },
  {
    "id": 423,
    "character": "賢",
    "strokes": 16,
    "readings": {
      "kun": [
        {
          "furigana": "かしこ",
          "romanji": "kashiko"
        }
      ],
      "on": [
        {
          "furigana": "ケン",
          "romanji": "ken"
        }
      ]
    },
    "meanings": {
      "id": "cerdik, pandai, bijaksana, arif",
      "en": "wise, clever, intelligent"
    },
    "examples": [
      {
        "word": "賢い",
        "furigana": "かしこい",
        "romanji": "kashikoi",
        "meanings": {
          "id": "cerdik, pandai",
          "en": "wise, clever"
        },
        "id": 1
      },
      {
        "word": "賢明",
        "furigana": "けんめい",
        "romanji": "kenmei",
        "meanings": {
          "id": "bijaksana, arif",
          "en": "intelligent, wise"
        },
        "id": 2
      }
    ]
  },
  {
    "id": 424,
    "character": "縦",
    "strokes": 16,
    "readings": {
      "kun": [
        {
          "furigana": "たて",
          "romanji": "tate"
        }
      ],
      "on": [
        {
          "furigana": "ジュウ",
          "romanji": "juu"
        }
      ]
    },
    "meanings": {
      "id": "garis tegak, vertikal, bebas menyaksikan",
      "en": "vertical line, to view freely"
    },
    "examples": [
      {
        "word": "縦線",
        "furigana": "じゅうせん",
        "romanji": "juusen",
        "meanings": {
          "id": "garis tegak, vertikal",
          "en": "vertical line"
        },
        "id": 1
      },
      {
        "word": "縦覧",
        "furigana": "じゅうらん",
        "romanji": "juuran",
        "meanings": {
          "id": "bebas menyaksikan",
          "en": "to view freely"
        },
        "id": 2
      }
    ]
  },
  {
    "id": 425,
    "character": "糖",
    "strokes": 16,
    "readings": {
      "kun": [],
      "on": [
        {
          "furigana": "トウ",
          "romanji": "tou"
        }
      ]
    },
    "meanings": {
      "id": "penyakit diabetes",
      "en": "diabetes"
    },
    "examples": [
      {
        "word": "糖尿病",
        "furigana": "とうにょうびょう",
        "romanji": "tounyoubyou",
        "meanings": {
          "id": "penyakit diabetes",
          "en": "diabetes"
        },
        "id": 1
      }
    ]
  },
  {
    "id": 426,
    "character": "操",
    "strokes": 16,
    "readings": {
      "kun": [
        {
          "furigana": "あやつ",
          "romanji": "ayatsu"
        },
        {
          "furigana": "みさお",
          "romanji": "misao"
        }
      ],
      "on": [
        {
          "furigana": "ソウ",
          "romanji": "sou"
        }
      ]
    },
    "meanings": {
      "id": "menangani, kesucian, penanganan",
      "en": "to handle, chastity, operation"
    },
    "examples": [
      {
        "word": "操る",
        "furigana": "あやつる",
        "romanji": "ayatsuru",
        "meanings": {
          "id": "menangani",
          "en": "to handle"
        },
        "id": 1
      },
      {
        "word": "操",
        "furigana": "みさお",
        "romanji": "misao",
        "meanings": {
          "id": "kesucian",
          "en": "chastity"
        },
        "id": 2
      },
      {
        "word": "操作",
        "furigana": "そうさ",
        "romanji": "sousa",
        "meanings": {
          "id": "penanganan",
          "en": "operation"
        },
        "id": 3
      }
    ]
  },
  {
    "id": 427,
    "character": "燥",
    "strokes": 17,
    "readings": {
      "kun": [],
      "on": [
        {
          "furigana": "ソウ",
          "romanji": "sou"
        }
      ]
    },
    "meanings": {
      "id": "kering",
      "en": "dry"
    },
    "examples": [
      {
        "id": 1,
        "word": "乾燥",
        "furigana": "かんそう",
        "romanji": "kansou",
        "meanings": {
          "id": "kering",
          "en": "dryness, aridity"
        }
      }
    ]
  },
  {
    "id": 428,
    "character": "謝",
    "strokes": 17,
    "readings": {
      "kun": [
        {
          "furigana": "あやま",
          "romanji": "ayama"
        }
      ],
      "on": [
        {
          "furigana": "シャ",
          "romanji": "sha"
        }
      ]
    },
    "meanings": {
      "id": "meminta maaf",
      "en": "to apologize"
    },
    "examples": [
      {
        "word": "謝る",
        "furigana": "あやまる",
        "romanji": "ayamaru",
        "meanings": {
          "id": "meminta maaf",
          "en": "to apologize"
        },
        "id": 1
      },
      {
        "id": 2,
        "word": "謝罪する",
        "furigana": "しゃざいする",
        "romanji": "shazai suru",
        "meanings": {
          "id": "meminta maaf",
          "en": "to apologize"
        }
      }
    ]
  },
  {
    "id": 429,
    "character": "講",
    "strokes": 17,
    "readings": {
      "kun": [],
      "on": [
        {
          "furigana": "コウ",
          "romanji": "kou"
        }
      ]
    },
    "meanings": {
      "id": "penceramah, dosen",
      "en": "lecturer, speaker"
    },
    "examples": [
      {
        "word": "講師",
        "furigana": "こうし",
        "romanji": "koushi",
        "meanings": {
          "id": "penceramah, dosen",
          "en": "lecturer, speaker"
        },
        "id": 1
      }
    ]
  },
  {
    "id": 430,
    "character": "購",
    "strokes": 17,
    "readings": {
      "kun": [],
      "on": [
        {
          "furigana": "コウ",
          "romanji": "kou"
        }
      ]
    },
    "meanings": {
      "id": "pembelian",
      "en": "purchase"
    },
    "examples": [
      {
        "word": "購入",
        "furigana": "こうにゅう",
        "romanji": "kounyuu",
        "meanings": {
          "id": "pembelian",
          "en": "purchase"
        },
        "id": 1
      }
    ]
  },
  {
    "id": 431,
    "character": "覧",
    "strokes": 17,
    "readings": {
      "kun": [],
      "on": [
        {
          "furigana": "ラン",
          "romanji": "ran"
        }
      ]
    },
    "meanings": {
      "id": "tontonan",
      "en": "viewing, spectacle"
    },
    "examples": [
      {
        "word": "観覧",
        "furigana": "かんらん",
        "romanji": "kanran",
        "meanings": {
          "id": "tontonan",
          "en": "viewing, spectacle"
        },
        "id": 1
      }
    ]
  },
  {
    "id": 432,
    "character": "厳",
    "strokes": 17,
    "readings": {
      "kun": [
        {
          "furigana": "きび",
          "romanji": "kibi"
        },
        {
          "furigana": "おごそ",
          "romanji": "ogoso"
        }
      ],
      "on": [
        {
          "furigana": "ゲン",
          "romanji": "gen"
        },
        {
          "furigana": "ゴン",
          "romanji": "gon"
        }
      ]
    },
    "meanings": {
      "id": "ketat, tegas, khidmat, serius, berat, keras, khidmat, serius",
      "en": "strict, stern, solemn, serious, heavy, hard"
    },
    "examples": [
      {
        "word": "厳しい",
        "furigana": "きびしい",
        "romanji": "kibishii",
        "meanings": {
          "id": "ketat, tegas",
          "en": "strict, stern"
        },
        "id": 1
      },
      {
        "word": "厳か",
        "furigana": "おごそか",
        "romanji": "ogosoka",
        "meanings": {
          "id": "khidmat, serius",
          "en": "solemn, serious"
        },
        "id": 2
      },
      {
        "word": "厳重",
        "furigana": "げんじゅう",
        "romanji": "genjuu",
        "meanings": {
          "id": "berat, keras, serius",
          "en": "heavy, hard, serious"
        },
        "id": 3
      },
      {
        "id": 4,
        "word": "荘厳",
        "furigana": "そうごん",
        "romanji": "shougon",
        "meanings": {
          "id": "khidmat, serius, agung",
          "en": "solemn, dignified, magnificent"
        }
      }
    ]
  },
  {
    "id": 433,
    "character": "療",
    "strokes": 17,
    "readings": {
      "kun": [],
      "on": [
        {
          "furigana": "リョウ",
          "romanji": "ryou"
        }
      ]
    },
    "meanings": {
      "id": "pengobatan",
      "en": "medical treatment"
    },
    "examples": [
      {
        "word": "治療",
        "furigana": "ちりょう",
        "romanji": "chiryou",
        "meanings": {
          "id": "pengobatan",
          "en": "medical treatment"
        },
        "id": 1
      }
    ]
  },
  {
    "id": 434,
    "character": "濯",
    "strokes": 17,
    "readings": {
      "kun": [
        {
          "furigana": "すす",
          "romanji": "susu"
        }
      ],
      "on": [
        {
          "furigana": "タク",
          "romanji": "taku"
        }
      ]
    },
    "meanings": {
      "id": "membilas, cucian",
      "en": "to rinse, laundry"
    },
    "examples": [
      {
        "word": "濯ぐ",
        "furigana": "すすぐ",
        "romanji": "susugu",
        "meanings": {
          "id": "membilas",
          "en": "to rinse"
        },
        "id": 1
      },
      {
        "word": "洗濯",
        "furigana": "せんたく",
        "romanji": "sentaku",
        "meanings": {
          "id": "cucian",
          "en": "laundry"
        },
        "id": 2
      }
    ]
  }
]