{
  "items": [
    {
      "id": 1,
      "category": {
        "id": "KATA_SAMBUNG",
        "en": "CONJUNCTIONS"
      },
      "vocabulary": [
        { "id": 2, "kanji": "それから", "hiragana": "それから", "romaji": "sorekara", "meanings": { "en": "then, after that", "id": "kemudian, setelah itu" } },
        { "id": 3, "kanji": "では, それでは", "hiragana": "では, それでは", "romaji": "dewa, soredewa", "meanings": { "en": "well then, if so", "id": "kalau begitu" } },
        { "id": 4, "kanji": "でも", "hiragana": "でも", "romaji": "demo", "meanings": { "en": "but", "id": "tetapi" } },
        { "id": 5, "kanji": "しかし", "hiragana": "しかし", "romaji": "shikashi", "meanings": { "en": "however", "id": "tetapi" } },
        { "id": 6, "kanji": "あまり", "hiragana": "あまり", "romaji": "amari", "meanings": { "en": "not very", "id": "agak, tidak begitu.." } },
        { "id": 7, "kanji": "より", "hiragana": "より", "romaji": "yori", "meanings": { "en": "than", "id": "daripada" } },
        { "id": 8, "kanji": "ほうが", "hiragana": "ほうが", "romaji": "hou ga", "meanings": { "en": "more", "id": "lebih" } },
        { "id": 9, "kanji": "また", "hiragana": "また", "romaji": "mata", "meanings": { "en": "again, also", "id": "lagi, lagi pula" } },
        { "id": 10, "kanji": "の前に", "hiragana": "のまえに", "romaji": "no mae ni", "meanings": { "en": "before", "id": "sebelum.." } },
        { "id": 11, "kanji": "-たあとで, -の後で", "hiragana": "-たあとで, -のあとで", "romaji": "-ta ato de, -no ato de", "meanings": { "en": "after", "id": "sesudah..." } },
        { "id": 12, "kanji": "と一緒に", "hiragana": "といっしょに", "romaji": "to issho ni", "meanings": { "en": "together with", "id": "bersama dengan ..." } }
      ]
    },
    {
      "id": 2,
      "category": {
        "id": "KATA_KETERANGAN",
        "en": "ADVERBS"
      },
      "vocabulary": [
        { "id": 1, "kanji": "いちばん", "hiragana": "いちばん", "romaji": "ichiban", "meanings": { "en": "number one, most", "id": "nomor satu, paling" } },
        { "id": 2, "kanji": "おなじ", "hiragana": "おなじ", "romaji": "onaji", "meanings": { "en": "same", "id": "sama" } },
        { "id": 3, "kanji": "たくさん", "hiragana": "たくさん", "romaji": "takusan", "meanings": { "en": "many", "id": "banyak" } },
        { "id": 4, "kanji": "大勢", "hiragana": "おおぜい", "romaji": "oozei", "meanings": { "en": "many (people), crowd", "id": "banyak (manusia), ramai" } },
        { "id": 5, "kanji": "結構", "hiragana": "けっこう", "romaji": "kekkou", "meanings": { "en": "enough, good", "id": "cukup, bagus" } },
        { "id": 6, "kanji": "とても", "hiragana": "とても", "romaji": "totemo", "meanings": { "en": "very", "id": "sangat" } },
        { "id": 7, "kanji": "少し", "hiragana": "すこし", "romaji": "sukoshi", "meanings": { "en": "a little", "id": "sedikit, agak" } },
        { "id": 8, "kanji": "少ない", "hiragana": "すくない", "romaji": "sukunai", "meanings": { "en": "few", "id": "kurang" } },
        { "id": 9, "kanji": "皆, 皆さん", "hiragana": "みな, みなさん", "romaji": "mina, minasan", "meanings": { "en": "everyone", "id": "semua, setiap orang, anda sekalian" } },
        { "id": 10, "kanji": "全部", "hiragana": "ぜんぶ", "romaji": "zenbu", "meanings": { "en": "all", "id": "seluruh, semua" } },
        { "id": 11, "kanji": "半分", "hiragana": "はんぶん", "romaji": "hanbun", "meanings": { "en": "half", "id": "separuh, setengah" } },
        { "id": 12, "kanji": "たぶん", "hiragana": "たぶん", "romaji": "tabun", "meanings": { "en": "maybe", "id": "barangkali" } },
        { "id": 13, "kanji": "だんだん", "hiragana": "だんだん", "romaji": "dandan", "meanings": { "en": "gradually", "id": "lambat laun" } },
        { "id": 14, "kanji": "ちょっと", "hiragana": "ちょっと", "romaji": "chotto", "meanings": { "en": "a little, a bit", "id": "agak, sedikit, sebentar" } }
      ]
    }
  ]
}
