{
  "id": 247,
  "character": "酒",
  "strokes": 10,
  "readings": {
    "kun": [
      {
        "id": 1,
        "furigana": "さけ",
        "romanji": "sake",
        "examples": [
          {
            "id": 1,
            "word": "酒",
            "furigana": "さけ",
            "romanji": "sake",
            "meanings": {
              "id": "minuman keras",
              "en": "alcohol"
            },
            "sentences": []
          }
        ]
      },
      {
        "id": 2,
        "furigana": "さか",
        "romanji": "saka",
        "examples": [
          {
            "id": 1,
            "word": "酒屋",
            "furigana": "さかや",
            "romanji": "sakaya",
            "meanings": {
              "id": "toko arak",
              "en": "liquor store"
            },
            "sentences": []
          }
        ]
      }
    ],
    "on": [
      {
        "id": 1,
        "furigana": "シュ",
        "romanji": "shu",
        "examples": [
          {
            "id": 1,
            "word": "日本酒",
            "furigana": "にほんしゅ",
            "romanji": "nihonshu",
            "meanings": {
              "id": "arak Jepang",
              "en": "sake"
            },
            "sentences": []
          }
        ]
      }
    ],
    "exception": null
  },
  "meanings": {
    "id": "minuman keras, toko arak, arak Jepang",
    "en": "alcohol, liquor store, sake"
  }
}