{
  "id": 44,
  "character": "件",
  "strokes": 6,
  "readings": {
    "kun": [],
    "on": [
      {
        "furigana": "ケン",
        "romanji": "ken",
        "examples": [
          {
            "id": 1,
            "word": "事件",
            "furigana": "じけん",
            "romanji": "jiken",
            "meanings": {
              "id": "insiden, kejadian",
              "en": "incident"
            },
            "sentences": []
          }
        ]
      }
    ],
    "exception": null
  },
  "meanings": {
    "id": "insiden, kejadian",
    "en": "matter, case"
  }
}