{
  "id": 81,
  "character": "快",
  "strokes": 7,
  "readings": {
    "kun": [
      {
        "id": 1,
        "furigana": "こころよ",
        "romanji": "kokoroyo",
        "examples": [
          {
            "id": 1,
            "word": "快い",
            "furigana": "こころよい",
            "romanji": "kokoroyoi",
            "meanings": {
              "id": "nyaman",
              "en": "pleasant"
            },
            "sentences": []
          }
        ]
      }
    ],
    "on": [
      {
        "id": 1,
        "furigana": "カイ",
        "romanji": "kai",
        "examples": [
          {
            "id": 1,
            "word": "快晴",
            "furigana": "かいせい",
            "romanji": "kaisei",
            "meanings": {
              "id": "cuaca baik",
              "en": "fine weather"
            },
            "sentences": []
          }
        ]
      }
    ],
    "exception": null
  },
  "meanings": {
    "id": "nyaman",
    "en": "comfortable"
  }
}