{
  "id": 82,
  "character": "春",
  "strokes": 9,
  "readings": {
    "kun": [
      {
        "id": 1,
        "furigana": "はる",
        "romanji": "haru",
        "examples": [
          {
            "id": 1,
            "word": "春",
            "furigana": "はる",
            "romanji": "haru",
            "meanings": {
              "id": "musim semi",
              "en": "spring"
            }
          }
        ]
      }
    ],
    "on": [
      {
        "id": 1,
        "furigana": "シュン",
        "romanji": "shun",
        "examples": [
          {
            "id": 1,
            "word": "春季",
            "furigana": "しゅんき",
            "romanji": "shunki",
            "meanings": {
              "id": "musim semi",
              "en": "spring season"
            }
          }
        ]
      }
    ],
    "exception": null
  },
  "meanings": {
    "id": "musim semi",
    "en": "spring"
  }
}