{
  "id": 290,
  "character": "超",
  "strokes": 12,
  "readings": {
    "kun": [
      {
        "furigana": "こ",
        "romanji": "ko",
        "examples": [
          {
            "id": 1,
            "word": "超える",
            "furigana": "こえる",
            "romanji": "koeru",
            "meanings": {
              "id": "melampaui",
              "en": "to exceed"
            }
          }
        ]
      }
    ],
    "on": [
      {
        "furigana": "チョウ",
        "romanji": "chou",
        "examples": [
          {
            "id": 2,
            "word": "超能力",
            "furigana": "ちょうのうりょく",
            "romanji": "chounouryoku",
            "meanings": {
              "id": "kekuatan supranatural",
              "en": "supernatural power"
            }
          }
        ]
      }
    ],
    "exception": null
  },
  "meanings": {
    "id": "melampaui, kekuatan supranatural",
    "en": "to exceed, supernatural power"
  }
}