{
  "id": 291,
  "character": "喫",
  "strokes": 12,
  "readings": {
    "kun": [],
    "on": [
      {
        "id": 1,
        "furigana": "キツ",
        "romanji": "kitsu",
        "examples": [
          {
            "id": 1,
            "word": "喫煙",
            "furigana": "きつえん",
            "romanji": "kitsuen",
            "meanings": {
              "id": "merokok",
              "en": "smoking"
            },
            "sentences": []
          }
        ]
      }
    ],
    "exception": {
      "examples": [
        {
          "id": 1,
          "word": "喫茶店",
          "furigana": "きっさてん",
          "romanji": "kissaten",
          "meanings": {
            "id": "kafe, warung kopi",
            "en": "cafe, coffee shop"
          },
          "sentences": []
        }
      ]
    }
  },
  "meanings": {
    "id": "merokok, kafe, warung kopi",
    "en": "smoke, cafe, coffee shop"
  }
}