[
  {
    "id": 412,
    "character": "構",
    "strokes": 14,
    "readings": {
      "kun": [ { "furigana": "かま", "romanji": "kama" } ],
      "on": [ { "furigana": "コウ", "romanji": "kou" } ]
    },
    "meanings": {
      "id": "membangun, struktur, susunan",
      "en": "build, structure, composition"
    },
    "examples": [
      { "word": "構える", "furigana": "かまえる", "romanji": "kamaeru", "id": 412, "meanings": { "id": "membangun", "en": "to build" } },
      { "word": "構造", "furigana": "こうぞう", "romanji": "kouzou", "id": 412, "meanings": { "id": "struktur, susunan", "en": "structure, composition" } }
    ]
  },
  {
    "id": 413,
    "character": "静",
    "strokes": 14,
    "readings": {
      "kun": [ { "furigana": "しず", "romanji": "shizu" } ],
      "on": [ { "furigana": "セイ", "romanji": "sei" }, { "furigana": "ジョウ", "romanji": "jou" } ]
    },
    "meanings": {
      "id": "tenang, sunyi, tidak bergerak, pembuluh darah",
      "en": "quiet, calm, still, blood vessel"
    },
    "examples": [
      { "word": "静止", "furigana": "せいし", "romanji": "seishi", "id": 413, "meanings": { "id": "tidak bergerak", "en": "still" } },
      { "word": "静脈", "furigana": "じょうみゃく", "romanji": "joumyaku", "id": 413, "meanings": { "id": "pembuluh darah", "en": "blood vessel" } }
    ]
  },
  {
    "id": 414,
    "character": "鳴",
    "strokes": 14,
    "readings": {
      "kun": [ { "furigana": "な", "romanji": "na" } ],
      "on": [ { "furigana": "メイ", "romanji": "mei" } ]
    },
    "meanings": {
      "id": "(binatang) berbunyi, guntur, geledek",
      "en": "animal sound, thunder, lightning"
    },
    "examples": [
      { "word": "鳴く", "furigana": "なく", "romanji": "naku", "id": 414, "meanings": { "id": "(binatang) berbunyi", "en": "animal sound" } },
      { "word": "雷鳴", "furigana": "らいめい", "romanji": "raimei", "id": 414, "meanings": { "id": "guntur, geledek", "en": "thunder, lightning" } }
    ]
  },
  {
    "id": 415,
    "character": "誤",
    "strokes": 14,
    "readings": {
      "kun": [ { "furigana": "あやま", "romanji": "ayama" } ],
      "on": [ { "furigana": "ゴ", "romanji": "go" } ]
    },
    "meanings": {
      "id": "salah, keliru, salah paham",
      "en": "wrong, mistake, misunderstanding"
    },
    "examples": [
      { "word": "誤る", "furigana": "あやまる", "romanji": "ayamaru", "id": 415, "meanings": { "id": "salah, keliru", "en": "wrong, mistake" } },
      { "word": "誤解", "furigana": "ごかい", "romanji": "gokai", "id": 415, "meanings": { "id": "salah paham", "en": "misunderstanding" } }
    ]
  },
  {
    "id": 416,
    "character": "認",
    "strokes": 14,
    "readings": {
      "kun": [ { "furigana": "みと", "romanji": "mito" } ],
      "on": [ { "furigana": "ニン", "romanji": "nin" } ]
    },
    "meanings": {
      "id": "mengakui, kenal, paham",
      "en": "admit, recognize, understand"
    },
    "examples": [
      { "word": "認める", "furigana": "みとめる", "romanji": "mitomeru", "id": 416, "meanings": { "id": "mengakui", "en": "admit" } },
      { "word": "認識", "furigana": "にんしき", "romanji": "ninshiki", "id": 416, "meanings": { "id": "kenal, paham", "en": "recognize, understand" } }
    ]
  },
  {
    "id": 417,
    "character": "緒",
    "strokes": 14,
    "readings": {
      "kun": [ { "furigana": "お", "romanji": "o" } ],
      "on": [ { "furigana": "ショ", "romanji": "sho" }, { "furigana": "チョ", "romanji": "cho" } ]
    },
    "meanings": {
      "id": "tali, bersama-sama",
      "en": "cord, together"
    },
    "examples": [
      { "word": "緒", "furigana": "お", "romanji": "o", "id": 417, "meanings": { "id": "tali", "en": "cord" } },
      { "word": "一緒", "furigana": "いっしょ", "romanji": "issho", "id": 417, "meanings": { "id": "bersama-sama", "en": "together" } }
    ]
  },
  {
    "id": 418,
    "character": "緑",
    "strokes": 14,
    "readings": {
      "kun": [ { "furigana": "みどり", "romanji": "midori" } ],
      "on": [ { "furigana": "リョク", "romanji": "ryoku" }, { "furigana": "ロク", "romanji": "roku" } ]
    },
    "meanings": {
      "id": "hijau, teh hijau",
      "en": "green, green tea"
    },
    "examples": [
      { "word": "緑", "furigana": "みどり", "romanji": "midori", "id": 418, "meanings": { "id": "hijau", "en": "green" } },
      { "word": "緑茶", "furigana": "りょくちゃ", "romanji": "ryokucha", "id": 418, "meanings": { "id": "teh hijau", "en": "green tea" } }
    ]
  },
  {
    "id": 419,
    "character": "練",
    "strokes": 14,
    "readings": {
      "kun": [ { "furigana": "ね", "romanji": "ne" } ],
      "on": [ { "furigana": "レン", "romanji": "ren" } ]
    },
    "meanings": {
      "id": "meremas, latihan",
      "en": "knead, practice"
    },
    "examples": [
      { "word": "練る", "furigana": "ねる", "romanji": "neru", "id": 419, "meanings": { "id": "meremas", "en": "knead" } },
      { "word": "練習", "furigana": "れんしゅう", "romanji": "renshuu", "id": 419, "meanings": { "id": "latihan", "en": "practice" } }
    ]
  },
  {
    "id": 420,
    "character": "演",
    "strokes": 14,
    "readings": {
      "kun": [],
      "on": [ { "furigana": "エン", "romanji": "en" } ]
    },
    "meanings": {
      "id": "pidato, orasi",
      "en": "speech, oration"
    },
    "examples": [
      { "word": "演説", "furigana": "えんぜつ", "romanji": "enzetsu", "id": 420, "meanings": { "id": "pidato, orasi", "en": "speech, oration" } }
    ]
  },
  {
    "id": 421,
    "character": "察",
    "strokes": 14,
    "readings": {
      "kun": [],
      "on": [ { "furigana": "サツ", "romanji": "satsu" } ]
    },
    "meanings": {
      "id": "polisi",
      "en": "police"
    },
    "examples": [
      { "word": "警察", "furigana": "けいさつ", "romanji": "keisatsu", "id": 421, "meanings": { "id": "polisi", "en": "police" } }
    ]
  },
  {
    "id": 422,
    "character": "際",
    "strokes": 14,
    "readings": {
      "kun": [ { "furigana": "きわ", "romanji": "kiwa" }, { "furigana": "ぎわ", "romanji": "giwa" } ],
      "on": [ { "furigana": "サイ", "romanji": "sai" } ]
    },
    "meanings": {
      "id": "menyolok, menonjol, cara penanganan, internasional",
      "en": "stand out, handling method, international"
    },
    "examples": [
      { "word": "際立つ", "furigana": "きわだつ", "romanji": "kiwadatsu", "id": 422, "meanings": { "id": "menyolok, menonjol", "en": "stand out" } },
      { "word": "手際", "furigana": "てぎわ", "romanji": "tegiwa", "id": 422, "meanings": { "id": "cara penanganan", "en": "handling method" } },
      { "word": "国際", "furigana": "こくさい", "romanji": "kokusai", "id": 422, "meanings": { "id": "internasional", "en": "international" } }
    ]
  }
]
